demeterchain/__init__.py
demeterchain/chains/__init__.py
demeterchain/chains/retrieval_qa.py
demeterchain/data_modules/__init__.py
demeterchain/data_modules/context_prefix_tree.py
demeterchain/llms/__init__.py
demeterchain/llms/chat_completions_llm.py
demeterchain/loaders/__init__.py
demeterchain/loaders/text_loader.py
demeterchain/models/__init__.py
demeterchain/models/base.py
demeterchain/models/generative_model.py
demeterchain/retrievers/__init__.py
demeterchain/retrievers/base.py
demeterchain/retrievers/pyserini_bm25.py
demeterchain/retrievers/rank_bm25.py
demeterchain/splitters/__init__.py
demeterchain/splitters/text_splitter.py
demeterchain/utils/__init__.py
demeterchain/utils/config.py
demeterchain/utils/data.py
demeterchain/utils/template.py
demeterchain-1.0.2.dist-info/LICENSE
demeterchain-1.0.2.dist-info/METADATA
demeterchain-1.0.2.dist-info/WHEEL
demeterchain-1.0.2.dist-info/top_level.txt
demeterchain-1.0.2.dist-info/RECORD
