Metadata-Version: 2.1
Name: demeterchain
Version: 1.0.2
Summary: A set of data tools in Python
Home-page: https://github.com/NCHU-NLP-Lab/demeterchain
Download-URL: https://pypi.org/project/demeterchain/
Author: WenChuan Hsu
Author-email: wenchuan19991111@gmail.com
License: MIT
Classifier: Programming Language :: Python :: 3.8
Classifier: Programming Language :: Python :: 3.9
Classifier: Programming Language :: Python :: 3.10
Requires-Python: >=3.8
License-File: LICENSE
Requires-Dist: torch
Requires-Dist: torchaudio
Requires-Dist: torchvision
Requires-Dist: bitsandbytes >=0.41.1
Requires-Dist: transformers <=4.40.0,>=4.36.0
Requires-Dist: accelerate >=0.21.0
Requires-Dist: scipy
Provides-Extra: dev
Requires-Dist: pyserini ==0.22.1 ; extra == 'dev'
Requires-Dist: faiss-cpu ==1.7.4 ; extra == 'dev'
Requires-Dist: rank-bm25 ; extra == 'dev'
